twigram/__init__.py
twigram/twitter.py
TwiGram-1.1.0.dist-info/LICENSE
TwiGram-1.1.0.dist-info/METADATA
TwiGram-1.1.0.dist-info/WHEEL
TwiGram-1.1.0.dist-info/top_level.txt
TwiGram-1.1.0.dist-info/RECORD
