Metadata-Version: 2.1
Name: TwiGram
Version: 1.1.0
Summary: Simple python package for download tweet from Twitter
Author: Matin Baloochestani (Matin-B)
Author-email: MatiinBaloochestani@Gmail.com
Keywords: python,twitter
Classifier: Development Status :: 1 - Planning
Classifier: Intended Audience :: Developers
Classifier: Programming Language :: Python :: 3
Classifier: Operating System :: Unix
Classifier: Operating System :: MacOS :: MacOS X
Classifier: Operating System :: Microsoft :: Windows
License-File: LICENSE
Requires-Dist: requests
